{
  "title": "Barbara Lee, la favorita para la alcaldía de Oakland",
  "summary": "La ex representante Barbara Lee se ha convertido en la candidata favorita para la alcaldía de la ciudad de Oakland, California. Sin embargo, su principal rival ha ganado terreno al posicionarse como el candidato del cambio.",
  "url": "https://www.nytimes.com/2025/04/13/us/oakland-mayor-barbara-lee-loren-taylor.html",
  "image": "https://static01.nyt.com/images/2025/04/11/multimedia/11nat-oakland-mayor-qjwg/11nat-oakland-mayor-qjwg-facebookJumbo.jpg",
  "date": "13-04-2025"
}
